termchar_demo/__init__.py
termchar_demo/advanced_demo.py
termchar_demo/app.py
termchar_demo/app.tcss
termchar_demo/arrows.py
termchar_demo/background.md
termchar_demo/basic_demo.py
termchar_demo/buffer.py
termchar_demo/devices.py
termchar_demo/intro.md
termchar_demo-0.4.0.dist-info/LICENSE
termchar_demo-0.4.0.dist-info/METADATA
termchar_demo-0.4.0.dist-info/WHEEL
termchar_demo-0.4.0.dist-info/entry_points.txt
termchar_demo-0.4.0.dist-info/RECORD
