Metadata-Version: 2.3
Name: termchar-demo
Version: 0.4.0
Summary: Termination character demo, a playground to learn about serial communication.
License: MIT
Author: David Fokkema
Author-email: davidfokkema@icloud.com
Requires-Python: >=3.10,<4.0
Classifier: License :: OSI Approved :: MIT License
Classifier: Programming Language :: Python :: 3
Classifier: Programming Language :: Python :: 3.10
Classifier: Programming Language :: Python :: 3.11
Classifier: Programming Language :: Python :: 3.12
Classifier: Programming Language :: Python :: 3.13
Requires-Dist: textual (>=0.81.0,<0.82.0)
